mcp_snowflake_reader/__init__.py
mcp_snowflake_reader/main.py
mcp_snowflake_reader-0.2.1.dist-info/licenses/LICENSE
mcp_snowflake_reader-0.2.1.dist-info/METADATA
mcp_snowflake_reader-0.2.1.dist-info/WHEEL
mcp_snowflake_reader-0.2.1.dist-info/entry_points.txt
mcp_snowflake_reader-0.2.1.dist-info/top_level.txt
mcp_snowflake_reader-0.2.1.dist-info/RECORD
