Metadata-Version: 2.4
Name: mcp-snowflake-reader
Version: 0.2.1
Summary: Read-only MCP server for Snowflake databases
Author: Miseon Kim
License-Expression: MIT
Requires-Python: >=3.10
License-File: LICENSE
Requires-Dist: mcp>=1.6.0
Requires-Dist: python-dotenv>=1.0.0
Requires-Dist: snowflake-connector-python>=3.10.0
Dynamic: license-file
